sparsenn/__init__.py
sparsenn/ad.py
sparsenn/custom_types.py
sparsenn/linear.py
sparsenn/opt.py
sparsenn/utils.py
sparsenn-0.1.0.dist-info/WHEEL
sparsenn-0.1.0.dist-info/METADATA
sparsenn-0.1.0.dist-info/RECORD
